flask_webpack_js.py
flask_webpack_js-0.1.0.dist-info/LICENSE
flask_webpack_js-0.1.0.dist-info/METADATA
flask_webpack_js-0.1.0.dist-info/WHEEL
flask_webpack_js-0.1.0.dist-info/top_level.txt
flask_webpack_js-0.1.0.dist-info/RECORD
