Metadata-Version: 2.1
Name: flask-webpack-js
Version: 0.1.0
Summary: Use webpack bundles in flask jinja templates
Home-page: https://github.com/sullivan-sean/flask-webpack
Author: Sean Sullivan
Author-email: ssullivan61198@gmail.com
License: BSD
Platform: any
Classifier: Environment :: Web Environment
Classifier: Intended Audience :: Developers
Classifier: License :: OSI Approved :: BSD License
Classifier: Operating System :: OS Independent
Classifier: Programming Language :: Python
Classifier: Topic :: Internet :: WWW/HTTP :: Dynamic Content
Classifier: Topic :: Software Development :: Libraries :: Python Modules
Requires-Dist: Flask
